abin_sim/__init__.py
abin_sim/cli.py
abin_sim/config.py
abin_sim/core/file_manager.py
abin_sim/core/functions.py
abin_sim-1.2.10.dist-info/LICENSE
abin_sim-1.2.10.dist-info/METADATA
abin_sim-1.2.10.dist-info/WHEEL
abin_sim-1.2.10.dist-info/entry_points.txt
abin_sim-1.2.10.dist-info/RECORD
