Metadata-Version: 2.1
Name: abin-sim
Version: 1.2.10
Summary: ABIN é um CLI para interagir com a API do Vault e auxiliar os Desenvolvedores nos projetos da SIMTech
License: Beerware
Author: Bonatto
Author-email: andrebonatto@gmail.com
Requires-Python: >=3.10,<4.0
Classifier: Development Status :: 5 - Production/Stable
Classifier: Environment :: Console
Classifier: License :: Other/Proprietary License
Classifier: Natural Language :: Portuguese (Brazilian)
Classifier: Programming Language :: Python :: 3
Classifier: Programming Language :: Python :: 3.10
Classifier: Programming Language :: Python :: 3.11
Classifier: Programming Language :: Python :: 3.12
Classifier: Topic :: Utilities
Requires-Dist: dynaconf (>=3.1.12,<4.0.0)
Requires-Dist: pathlib3x (>=2.0.2.1,<3.0.0.0)
Requires-Dist: requests (>=2.28.2,<3.0.0)
Requires-Dist: rich (>=13.3.4,<14.0.0)
Requires-Dist: typer (>=0.7.0,<0.8.0)
